{
  "accordionProps": {
    "items": {
      "type": "AccordionItemDef[]",
      "description": "Array of { id, title, content, icon?, disabled? }."
    },
    "mode": {
      "type": "'single' | 'multi'",
      "default": "'single'",
      "description": "Whether multiple panels can be open at once."
    },
    "variant": {
      "type": "'default' | 'bordered' | 'filled' | 'minimal' | 'separated'",
      "default": "'default'",
      "description": "Visual style."
    },
    "chevronPosition": {
      "type": "'left' | 'right'",
      "default": "'right'",
      "description": "Where the expand chevron appears in the header."
    },
    "defaultOpen": {
      "type": "string[]",
      "description": "Initial open item ids (uncontrolled)."
    },
    "value": {
      "type": "string[]",
      "description": "Controlled open item ids."
    },
    "onChange": {
      "type": "(openIds: string[]) => void",
      "description": "Called when the set of open items changes."
    },
    "ariaLabel": {
      "type": "string",
      "description": "Accessible name for the accordion if needed."
    },
    "headingLevel": {
      "type": "1 | 2 | 3 | 4 | 5 | 6",
      "default": "3",
      "description": "Heading level used for each item title (h1-h6) so the page heading outline is correct."
    },
    "unmountOnCollapse": {
      "type": "boolean",
      "default": "false",
      "description": "Unmount panel content when collapsed (useful for heavy content that should not stay in the DOM)."
    },
    "className": {
      "type": "string",
      "description": "Additional CSS class for the accordion wrapper."
    }
  }
}
